rmgr/__init__.py
rmgr/core.py
rmgr/path.py
rmgr/proc.py
rmgr-0.0.3.dist-info/LICENSE
rmgr-0.0.3.dist-info/METADATA
rmgr-0.0.3.dist-info/WHEEL
rmgr-0.0.3.dist-info/top_level.txt
rmgr-0.0.3.dist-info/RECORD
