Metadata-Version: 2.1
Name: rmgr
Version: 0.0.3
Summary: UNKNOWN
Home-page: https://github.com/happyxianyu/rmgr
Author: happyxianyu
Author-email: happyxianyu623@outlook.com
License: Apache License 2.0
Platform: UNKNOWN
Requires-Python: >=3.8
Requires-Dist: cbutil
Requires-Dist: aiofile
Requires-Dist: awrand
